{
  "acid": "Happo",
  "weaker": "heikompi",
  "concentrationGraph.yAxis": "Tasapainokonsentraatio (mol/L)",
  "acid-base-solutions.name": "Happo-emäs-liuokset",
  "solution": "Liuos",
  "views": "Näkymät",
  "viewParticles": "Näytä hiukkaset",
  "weakAcid": "Heikko happo",
  "pHPaper": "pH-paperi",
  "pHMeter": "pH-mittari",
  "showWater": "Näytä liuotin",
  "translation.credits": "Rami Nuotio",
  "tests": "Kokeet",
  "strongBase": "Vahva emäs",
  "weak": "heikko",
  "molesPerLiter": "mol/L",
  "base": "Emäs",
  "testSolution": "Johdanto",
  "liters": "L",
  "liquid": "Neste",
  "strong": "vahva",
  "equilibriumConcentration": "Tasapaino-\nkonsentraatio",
  "weakBase": "Heikko emäs",
  "negligible": "merkityksetön",
  "water": "Vesi",
  "pattern.0value.1units": "{0}{1}",
  "pHColorKey": "pH-väriasteikko",
  "pH": "pH",
  "solutions": "Liuokset",
  "strength": "Voimakkuus:",
  "molecules": "Molekyylit",
  "pattern.0solution.1symbol": "{0} ({1})",
  "stronger": "vahvempi",
  "pattern.0label.1value": "{0}: {1}",
  "magnifying-glass-prototype.name": "Suurennuslasiprototyyppi",
  "initialConcentration": "Alkukonsentraatio:",
  "customSolution": "Oma liuos",
  "conductivity": "Sähkönjohtavuus",
  "strongAcid": "Vahva happo"
}