{
  "acid": "ácido",
  "weaker": "mais fraco",
  "concentrationGraph.yAxis": "concentração de equilíbrio (mol/L)",
  "acid-base-solutions.name": "Soluções ácido-base",
  "solution": "solução",
  "views": "ver",
  "viewParticles": "mostrar partículas",
  "weakAcid": "ácido fraco",
  "pHPaper": "papel de pH",
  "pHMeter": "medidor de pH",
  "showWater": "mostrar solvente",
  "tests": "testes",
  "strongBase": "base forte",
  "weak": "fraco",
  "molesPerLiter": "mol/L",
  "base": "base",
  "testSolution": "introdução",
  "liters": "L",
  "liquid": "Líquido",
  "strong": "forte",
  "equilibriumConcentration": "concentração\nEquilíbrio",
  "weakBase": "base fraca",
  "negligible": "insignificante",
  "water": "água",
  "pattern.0value.1units": "{0}{1}",
  "pHColorKey": "cor do pH",
  "pH": "pH",
  "solutions": "soluções",
  "strength": "força",
  "molecules": "moléculas",
  "pattern.0solution.1symbol": "{0} ({1})",
  "stronger": "mais forte",
  "pattern.0label.1value": "{0}: {1}",
  "magnifying-glass-prototype.name": "protótipo de lupa",
  "initialConcentration": "Concentração\nInicial:",
  "customSolution": "solução personalizada",
  "conductivity": "condutividade",
  "strongAcid": "ácido forte"
}